Workbook

Sheet EN
A1: Time period | B1: tenure | C1: dept | D1: fte
A2: 2015Q2 | B2: Casual | C2: Administrative Tribunals Support Service of Canada | D2: 13.6667
A3: 2015Q2 | B3: Casual | C3: Agriculture and Agri-Food Canada | D3: 145.333
A4: 2015Q2 | B4: Casual | C4: Atlantic Canada Opportunities Agency | D4: 14.3333
A5: 2015Q2 | B5: Casual | C5: Canada Border Services Agency | D5: 225
A6: 2015Q2 | B6: Casual | C6: Canada Economic Development for Quebec Regions | D6: 18.6667
A7: 2015Q2 | B7: Casual | C7: Canada Energy Regulator | D7: 3.5
A8: 2015Q2 | B8: Casual | C8: Canada School of Public Service | D8: 58.3333
A9: 2015Q2 | B9: Casual | C9: Canadian Dairy Commission | D9: 1
A10: 2015Q2 | B10: Casual | C10: Canadian Food Inspection Agency | D10: 1
A11: 2015Q2 | B11: Casual | C11: Canadian Grain Commission | D11: 3.66667
A12: 2015Q2 | B12: Casual | C12: Canadian Heritage | D12: 86.3333
A13: 2015Q2 | B13: Casual | C13: Canadian Human Rights Commission | D13: 6
... A14692: 2026Q1 | B14692: Total | C14692: Royal Canadian Mounted Police - Members | D14692: 19838.3

Sheet FR
A1: Période | B1: Durée d'emploi | C1: Ministère ou organisme | D1: Nombre d'équivalents temps plein
A2: =EN!A2 -> 2015Q2 | B2: =_xlfn.XLOOKUP(EN!B2,translation!$D$2:$D$6,translation!$E$2:$E$6,EN!B2,0,1) -> Employé occasionnel | C2: =_xlfn.XLOOKUP(EN!C2,translation!$A$2:$A$102,translation!$B$2:$B$102,EN!C2,0,1) -> Service canadien d’appui aux tribunaux administratifs | D2: =EN!D2 -> 13.6667
A3: =EN!A3 -> 2015Q2 | B3: =_xlfn.XLOOKUP(EN!B3,translation!$D$2:$D$6,translation!$E$2:$E$6,EN!B3,0,1) -> Employé occasionnel | C3: =_xlfn.XLOOKUP(EN!C3,translation!$A$2:$A$102,translation!$B$2:$B$102,EN!C3,0,1) -> Agriculture et Agroalimentaire Canada | D3: =EN!D3 -> 145.333
A4: =EN!A4 -> 2015Q2 | B4: =_xlfn.XLOOKUP(EN!B4,translation!$D$2:$D$6,translation!$E$2:$E$6,EN!B4,0,1) -> Employé occasionnel | C4: =_xlfn.XLOOKUP(EN!C4,translation!$A$2:$A$102,translation!$B$2:$B$102,EN!C4,0,1) -> Agence de promotion économique du Canada atlantique | D4: =EN!D4 -> 14.3333
A5: =EN!A5 -> 2015Q2 | B5: =_xlfn.XLOOKUP(EN!B5,translation!$D$2:$D$6,translation!$E$2:$E$6,EN!B5,0,1) -> Employé occasionnel | C5: =_xlfn.XLOOKUP(EN!C5,translation!$A$2:$A$102,translation!$B$2:$B$102,EN!C5,0,1) -> Agence des services frontaliers du Canada | D5: =EN!D5 -> 225
A6: =EN!A6 -> 2015Q2 | B6: =_xlfn.XLOOKUP(EN!B6,translation!$D$2:$D$6,translation!$E$2:$E$6,EN!B6,0,1) -> Employé occasionnel | C6: =_xlfn.XLOOKUP(EN!C6,translation!$A$2:$A$102,translation!$B$2:$B$102,EN!C6,0,1) -> Développement économique Canada pour les régions du Québec | D6: =EN!D6 -> 18.6667
A7: =EN!A7 -> 2015Q2 | B7: =_xlfn.XLOOKUP(EN!B7,translation!$D$2:$D$6,translation!$E$2:$E$6,EN!B7,0,1) -> Employé occasionnel | C7: =_xlfn.XLOOKUP(EN!C7,translation!$A$2:$A$102,translation!$B$2:$B$102,EN!C7,0,1) -> Régie de l’énergie du Canada | D7: =EN!D7 -> 3.5
A8: =EN!A8 -> 2015Q2 | B8: =_xlfn.XLOOKUP(EN!B8,translation!$D$2:$D$6,translation!$E$2:$E$6,EN!B8,0,1) -> Employé occasionnel | C8: =_xlfn.XLOOKUP(EN!C8,translation!$A$2:$A$102,translation!$B$2:$B$102,EN!C8,0,1) -> École de la fonction publique du Canada | D8: =EN!D8 -> 58.3333
A9: =EN!A9 -> 2015Q2 | B9: =_xlfn.XLOOKUP(EN!B9,translation!$D$2:$D$6,translation!$E$2:$E$6,EN!B9,0,1) -> Employé occasionnel | C9: =_xlfn.XLOOKUP(EN!C9,translation!$A$2:$A$102,translation!$B$2:$B$102,EN!C9,0,1) -> Commission canadienne du lait | D9: =EN!D9 -> 1
A10: =EN!A10 -> 2015Q2 | B10: =_xlfn.XLOOKUP(EN!B10,translation!$D$2:$D$6,translation!$E$2:$E$6,EN!B10,0,1) -> Employé occasionnel | C10: =_xlfn.XLOOKUP(EN!C10,translation!$A$2:$A$102,translation!$B$2:$B$102,EN!C10,0,1) -> Agence canadienne d’inspection des aliments | D10: =EN!D10 -> 1
A11: =EN!A11 -> 2015Q2 | B11: =_xlfn.XLOOKUP(EN!B11,translation!$D$2:$D$6,translation!$E$2:$E$6,EN!B11,0,1) -> Employé occasionnel | C11: =_xlfn.XLOOKUP(EN!C11,translation!$A$2:$A$102,translation!$B$2:$B$102,EN!C11,0,1) -> Commission canadienne des grains | D11: =EN!D11 -> 3.66667
A12: =EN!A12 -> 2015Q2 | B12: =_xlfn.XLOOKUP(EN!B12,translation!$D$2:$D$6,translation!$E$2:$E$6,EN!B12,0,1) -> Employé occasionnel | C12: =_xlfn.XLOOKUP(EN!C12,translation!$A$2:$A$102,translation!$B$2:$B$102,EN!C12,0,1) -> Patrimoine canadien | D12: =EN!D12 -> 86.3333
A13: =EN!A13 -> 2015Q2 | B13: =_xlfn.XLOOKUP(EN!B13,translation!$D$2:$D$6,translation!$E$2:$E$6,EN!B13,0,1) -> Employé occasionnel | C13: =_xlfn.XLOOKUP(EN!C13,translation!$A$2:$A$102,translation!$B$2:$B$102,EN!C13,0,1) -> Commission canadienne des droits de la personne | D13: =EN!D13 -> 6
... A14692: =EN!A14692 -> 2026Q1 | B14692: =_xlfn.XLOOKUP(EN!B14692,translation!$D$2:$D$6,translation!$E$2:$E$6,EN!B14692,0,1) -> Total | C14692: =_xlfn.XLOOKUP(EN!C14692,translation!$A$2:$A$102,translation!$B$2:$B$102,EN!C14692,0,1) -> Gendarmerie royale du Canada - Membres | D14692: =EN!D14692 -> 19838.3

Sheet translation
A1: dept_en | B1: dept_fr | D1: tenure_en | E1: tenure_fr
A2: Agriculture and Agri-Food Canada | B2: Agriculture et Agroalimentaire Canada | D2: Casual | E2: Employé occasionnel
A3: Office of the Auditor General of Canada | B3: Bureau du vérificateur général du Canada | D3: Indeterminate | E3: Durée indéterminée
A4: Public Service Commission of Canada | B4: Commission de la fonction publique du Canada | D4: Student | E4: Étudiant
A5: Global Affairs Canada | B5: Affaires mondiales Canada | D5: Term | E5: Durée déterminée
A6: Department of Finance Canada | B6: Ministère des Finances Canada | D6: missing | E6: Non disponible
A7: Environment and Climate Change Canada | B7: Environnement et Changement climatique Canada
A8: Office of the Governor General's Secretary | B8: Bureau du secrétaire du gouverneur général
A9: Office of the Superintendent of Financial Institutions Canada | B9: Bureau du surintendant des institutions financières Canada
A10: Canada Economic Development for Quebec Regions | B10: Développement économique Canada pour les régions du Québec
A11: Department of Justice Canada | B11: Ministère de la Justice Canada
A12: Employment and Social Development Canada | B12: Emploi et Développement social Canada
A13: Elections Canada | B13: Élections Canada
A14: Canadian Radio-television and Telecommunications Commission | B14: Conseil de la radiodiffusion et des télécommunications canadiennes
A15: National Defence | B15: Défense nationale
A16: Public Prosecution Service of Canada | B16: Service des poursuites pénales du Canada
A17: Veterans Affairs Canada | B17: Anciens Combattants Canada
A18: Health Canada | B18: Santé Canada
... A102: Housing, Infrastructure and Communities Canada | B102: Logement, Infrastructures et Collectivités Canada
